syncmqtt/__init__.py
syncmqtt/attr.py
syncmqtt/conn.py
syncmqtt/qtt.py
syncmqtt/sub.py
tests/__init__.py
tests/test_syncmqtt_pytest.py
syncmqtt-0.1.0.dist-info/LICENSE
syncmqtt-0.1.0.dist-info/METADATA
syncmqtt-0.1.0.dist-info/WHEEL
syncmqtt-0.1.0.dist-info/top_level.txt
syncmqtt-0.1.0.dist-info/RECORD
