Metadata-Version: 2.1
Name: syncmqtt
Version: 0.1.0
Summary: A library to synchronize MQTT topics with Python class attributes
Home-page: https://github.com/postor/sync-mqtt
Author: Josh Lin
Author-email: postor@gmail.com
Classifier: Programming Language :: Python :: 3
Classifier: License :: OSI Approved :: MIT License
Classifier: Operating System :: OS Independent
Requires-Python: >=3.6
License-File: LICENSE
Requires-Dist: paho-mqtt
